LICENSE.txt
MANIFEST.in
README.rst
setup.py
cake/__init__.py
cake/env.py
cake/error.py
cake/hub.py
cake/settings.py
cake/test/__init__.py
cake/test/hub_jukebox.py
cake/test/test_settings.py
hapicake.egg-info/PKG-INFO
hapicake.egg-info/SOURCES.txt
hapicake.egg-info/dependency_links.txt
hapicake.egg-info/requires.txt
hapicake.egg-info/top_level.txt