Metadata-Version: 1.0
Name: hapicake
Version: 0.1.1
Summary: a next generation hapipy
Home-page: https://github.com/HubSpot/hapicake
Author: prior
Author-email: mprior@hubspot.com
License: LICENSE.txt
Download-URL: https://github.com/HubSpot/hapicake/tarball/v0.1.1
Platform: any
